Metadata-Version: 2.4
Name: iflow-mcp_reader-mcp-server
Version: 0.1.0
Summary: Add your description here
Requires-Python: >=3.11
License-File: LICENSE
Requires-Dist: dotenv>=0.9.9
Requires-Dist: httpx>=0.28.1
Requires-Dist: mcp[cli]>=1.4.1
Dynamic: license-file
